{
  "mappings": {
    "tweet": {
      "properties": {
        "expanded_urls": {
          "type": "string",
          "analyzer": "whitespace"
        },
        "in_reply_to_status_id": {
          "type": "long"
        },
        "in_reply_to_user_id": {
          "type": "long"
        },
        "retweeted_status_id": {
          "type": "long"
        },
        "retweeted_status_timestamp": {
          "type": "date",
          "ignore_malformed": true,
          "format": "YYYY-MM-dd HH:mm:ss Z"
        },
        "retweeted_status_user_id": {
          "type": "long"
        },
        "source": {
          "type": "string"
        },
        "text": {
          "type": "string"
        },
        "timestamp": {
          "type": "date",
          "format": "YYYY-MM-dd HH:mm:ss Z",
          "ignore_malformed": true
        },
        "tweet_id": {
          "type": "long"
        }
      }
    }
  }
}
